README.md
pyproject.toml
setup.py
lastfm_cg/__init__.py
lastfm_cg/__main__.py
lastfm_cg/image_utils.py
lastfm_cg/lastfm_utils.py
lastfm_cg.egg-info/PKG-INFO
lastfm_cg.egg-info/SOURCES.txt
lastfm_cg.egg-info/dependency_links.txt
lastfm_cg.egg-info/entry_points.txt
lastfm_cg.egg-info/requires.txt
lastfm_cg.egg-info/top_level.txt