Metadata-Version: 2.1
Name: lastfm-cg
Version: 1.5.1
Summary: Generate covers collage from albums listened by a lastfm user.
Home-page: https://github.com/dbeley/lastfm_cg
Author: dbeley
Author-email: dbeley@protonmail.com
License: UNKNOWN
Platform: UNKNOWN
Classifier: Programming Language :: Python :: 3
Classifier: Operating System :: POSIX :: Linux
